<?xml version="1.0" encoding="utf-8"?>
<!DOCTYPE hibernate-mapping PUBLIC "-//Hibernate/Hibernate Mapping DTD 3.0//EN"
"http://hibernate.sourceforge.net/hibernate-mapping-3.0.dtd">
<!-- 
    Mapping file autogenerated by MyEclipse Persistence Tools
-->
<hibernate-mapping default-lazy="false">
    <class name="com.shoesback.po.Shoes" table="shoes" catalog="shoes">
        <id name="sid" type="java.lang.Integer">
            <column name="sid" />
            <generator class="native" />
        </id>
        <many-to-one name="types" class="com.shoesback.po.Types" fetch="select">
            <column name="stid" not-null="true">
                <comment>types外键</comment>
            </column>
        </many-to-one>
        <many-to-one name="brands" class="com.shoesback.po.Brands" fetch="select">
            <column name="sbid" not-null="true">
                <comment>brands外键</comment>
            </column>
        </many-to-one>
        <property name="snum" type="java.lang.String">
            <column name="snum" length="45">
                <comment>鞋标号</comment>
            </column>
        </property>
        <property name="sname" type="java.lang.String">
            <column name="sname" length="45" not-null="true">
                <comment>鞋名称</comment>
            </column>
        </property>
        <property name="sprices" type="java.lang.Float">
            <column name="sprices" precision="12" scale="0" not-null="true">
                <comment>鞋子价格</comment>
            </column>
        </property>
        <property name="sdiscount" type="java.lang.Integer">
            <column name="sdiscount" not-null="true">
                <comment>鞋库存量</comment>
            </column>
        </property>
        <property name="spubtime" type="java.sql.Timestamp">
            <column name="spubtime" length="19" not-null="true">
                <comment>上市时间</comment>
            </column>
        </property>
        <property name="sproducer" type="java.lang.String">
            <column name="sproducer" length="50">
                <comment>生产厂商</comment>
            </column>
        </property>
        <property name="sgender" type="java.lang.String">
            <column name="sgender" length="10" not-null="true">
                <comment>性别属性</comment>
            </column>
        </property>
        <property name="scolor" type="java.lang.String">
            <column name="scolor" length="45" not-null="true">
                <comment>鞋子颜色</comment>
            </column>
        </property>
        <property name="sinfo" type="java.lang.String">
            <column name="sinfo" length="65535">
                <comment>内容简介</comment>
            </column>
        </property>
        <property name="stimessold" type="java.lang.Integer">
            <column name="stimessold" not-null="true">
                <comment>鞋销量</comment>
            </column>
        </property>
        <property name="simage" type="java.lang.String">
            <column name="simage" length="200">
                <comment>鞋子图片url</comment>
            </column>
        </property>
        <property name="sdetail" type="java.lang.String">
            <column name="sdetail" length="45">
                <comment>详细 信息</comment>
            </column>
        </property>
        <property name="sintegral" type="java.lang.Float">
            <column name="sintegral" precision="12" scale="0">
                <comment>单件鞋总积分</comment>
            </column>
        </property>
        <property name="sdelete" type="java.lang.Integer">
            <column name="sdelete" not-null="true">
                <comment>鞋禁用标志</comment>
            </column>
        </property>
        <property name="sremarks" type="java.lang.String">
            <column name="sremarks" length="65535">
                <comment>备注</comment>
            </column>
        </property>
        <property name="sandroidimg" type="java.lang.String">
            <column name="sandroidimg" length="100">
                <comment>androidImage</comment>
            </column>
        </property>
        <set name="shoePhotoses" inverse="true">
            <key>
                <column name="sp_sid" not-null="true">
                    <comment>shoes外键</comment>
                </column>
            </key>
            <one-to-many class="com.shoesback.po.ShoePhotos" />
        </set>
        <set name="orderShoeses" inverse="true">
            <key>
                <column name="o_sid" not-null="true">
                    <comment>shoes外键</comment>
                </column>
            </key>
            <one-to-many class="com.shoesback.po.OrderShoes" />
        </set>
        <set name="spcifyResultses" inverse="true">
            <key>
                <column name="sp_sid" not-null="true">
                    <comment>spdify_shoes外键</comment>
                </column>
            </key>
            <one-to-many class="com.shoesback.po.SpcifyResults" />
        </set>
        <set name="commentses" inverse="true">
            <key>
                <column name="c_sid" not-null="true">
                    <comment>shoes外键</comment>
                </column>
            </key>
            <one-to-many class="com.shoesback.po.Comments" />
        </set>
        <set name="shoesizeses" inverse="true">
            <key>
                <column name="s_sid" not-null="true">
                    <comment>shoes外键</comment>
                </column>
            </key>
            <one-to-many class="com.shoesback.po.Shoesizes" />
        </set>
        <set name="secondKillses" inverse="true">
            <key>
                <column name="sk_sid" not-null="true">
                    <comment>shoes外键</comment>
                </column>
            </key>
            <one-to-many class="com.shoesback.po.SecondKills" />
        </set>
        <set name="shoesInquiryses" inverse="true">
            <key>
                <column name="sq_sid" not-null="true">
                    <comment>shoes外键</comment>
                </column>
            </key>
            <one-to-many class="com.shoesback.po.ShoesInquirys" />
        </set>
    </class>
</hibernate-mapping>
